MANIFEST.in
README.md
install-requirements.txt
setup.py
heptapod_paas_runner/VERSION
heptapod_paas_runner/__init__.py
heptapod_paas_runner/clever.py
heptapod_paas_runner/docker.py
heptapod_paas_runner/exceptions.py
heptapod_paas_runner/job.py
heptapod_paas_runner/local_docker.py
heptapod_paas_runner/paas_dispatcher.py
heptapod_paas_runner/paas_register.py
heptapod_paas_runner/paas_resource.py
heptapod_paas_runner/runner.py
heptapod_paas_runner/service_docker.py
heptapod_paas_runner/testing.py
heptapod_paas_runner/util.py
heptapod_paas_runner/version.py
heptapod_paas_runner.egg-info/PKG-INFO
heptapod_paas_runner.egg-info/SOURCES.txt
heptapod_paas_runner.egg-info/dependency_links.txt
heptapod_paas_runner.egg-info/entry_points.txt
heptapod_paas_runner.egg-info/requires.txt
heptapod_paas_runner.egg-info/top_level.txt
heptapod_paas_runner/grpc/__init__.py
heptapod_paas_runner/grpc/heptapod_paas_runner_pb2.py
heptapod_paas_runner/grpc/heptapod_paas_runner_pb2_grpc.py