Metadata-Version: 2.1
Name: heptapod-paas-runner
Version: 1.0.1
Summary: Heptapod Runner: Python utilities and subsystems
Home-page: https://foss.heptapod.net/heptapod/heptapod-paas-runner
Author: Georges Racinet
Author-email: georges.racinet@cloudcrane.io
License: GPLv3+
Keywords: hg mercurial git heptapod gitlab
Requires-Dist: overrides
Requires-Dist: toml
Requires-Dist: requests
Requires-Dist: six
Requires-Dist: ansi
Requires-Dist: grpcio~=1.71.0
Requires-Dist: protobuf~=6.30.2
